odysseusai/__init__.py
odysseusai/evaluation.py
odysseusai/example.py
odysseusai/llms.py
odysseusai/logging_llm.py
odysseusai/utils.py
src/__init__.py
src/evaluation.py
src/example.py
src/llms.py
src/logging_llm.py
src/utils.py
odysseusai-1.0.dist-info/METADATA
odysseusai-1.0.dist-info/WHEEL
odysseusai-1.0.dist-info/top_level.txt
odysseusai-1.0.dist-info/RECORD
