Metadata-Version: 2.1
Name: odysseusai
Version: 1.0
Summary: A package to log LLM models
Home-page: https://github.com/chziakas/odysseus_ai
Author: Christos Ziakas
Author-email: chziakas@gmail.com
License: UNKNOWN
Platform: UNKNOWN
Requires-Dist: openai
